traffic_light.v
module traffic_light(

    input clk,
    input reset,

    output reg red,
    output reg yellow,
    output reg green
);

parameter RED    = 2'b00;
parameter GREEN  = 2'b01;
parameter YELLOW = 2'b10;

reg [1:0] state;

reg [3:0] count;

always @(posedge clk or posedge reset)
begin

    if(reset)
    begin
        state <= RED;
        count <= 0;
    end

    else
    begin

        case(state)

            RED:
            begin

                if(count == 5)
                begin
                    state <= GREEN;
                    count <= 0;
                end

                else
                    count <= count + 1;
            end

            GREEN:
            begin

                if(count == 5)
                begin
                    state <= YELLOW;
                    count <= 0;
                end

                else
                    count <= count + 1;
            end

            YELLOW:
            begin

                if(count == 2)
                begin
                    state <= RED;
                    count <= 0;
                end

                else
                    count <= count + 1;
            end

        endcase
    end
end

always @(*)
begin

    red    = 0;
    yellow = 0;
    green  = 0;

    case(state)

        RED:
            red = 1;

        GREEN:
            green = 1;

        YELLOW:
            yellow = 1;

    endcase
end

endmodule

tb_traffic_light.v
`timescale 1ns/1ps

module tb_traffic_light;

reg clk;
reg reset;

wire red;
wire yellow;
wire green;

traffic_light uut(

    .clk(clk),
    .reset(reset),
    .red(red),
    .yellow(yellow),
    .green(green)
);

always #5 clk = ~clk;

initial
begin

    $dumpfile("dump.vcd");
    $dumpvars(0, tb_traffic_light);

    clk = 0;
    reset = 1;

    #10;
    reset = 0;

    #200;

    $finish;
end

initial
begin

    $monitor(
    "Time=%0t RED=%b YELLOW=%b GREEN=%b",
    $time,
    red,
    yellow,
    green
    );
end

endmodule

dump.vcd
$date
	Sun May 17 23:38:49 2026
$end
$version
	Icarus Verilog
$end
$timescale
	1ps
$end
$scope module tb_traffic_light $end
$var wire 1 ! yellow $end
$var wire 1 " red $end
$var wire 1 # green $end
$var reg 1 $ clk $end
$var reg 1 % reset $end
$scope module uut $end
$var wire 1 $ clk $end
$var wire 1 % reset $end
$var parameter 2 & GREEN $end
$var parameter 2 ' RED $end
$var parameter 2 ( YELLOW $end
$var reg 4 ) count [3:0] $end
$var reg 1 # green $end
$var reg 1 " red $end
$var reg 2 * state [1:0] $end
$var reg 1 ! yellow $end
$upscope $end
$upscope $end
$enddefinitions $end
$comment Show the parameter values. $end
$dumpall
b10 (
b0 '
b1 &
$end
#0
$dumpvars
b0 *
b0 )
1%
0$
0#
1"
0!
$end
#5000
1$
#10000
0$
0%
#15000
b1 )
1$
#20000
0$
#25000
b10 )
1$
#30000
0$
#35000
b11 )
1$
#40000
0$
#45000
b100 )
1$
#50000
0$
#55000
b101 )
1$
#60000
0$
#65000
1#
0"
b0 )
b1 *
1$
#70000
0$
#75000
b1 )
1$
#80000
0$
#85000
b10 )
1$
#90000
0$
#95000
b11 )
1$
#100000
0$
#105000
b100 )
1$
#110000
0$
#115000
b101 )
1$
#120000
0$
#125000
1!
0#
b0 )
b10 *
1$
#130000
0$
#135000
b1 )
1$
#140000
0$
#145000
b10 )
1$
#150000
0$
#155000
1"
0!
b0 )
b0 *
1$
#160000
0$
#165000
b1 )
1$
#170000
0$
#175000
b10 )
1$
#180000
0$
#185000
b11 )
1$
#190000
0$
#195000
b100 )
1$
#200000
0$
#205000
b101 )
1$
